davos/__init__.py
davos/__init__.pyi
davos/py.typed
davos/core/__init__.py
davos/core/__init__.pyi
davos/core/config.py
davos/core/config.pyi
davos/core/core.py
davos/core/core.pyi
davos/core/exceptions.py
davos/core/exceptions.pyi
davos/core/parsers.py
davos/core/parsers.pyi
davos/core/project.py
davos/core/project.pyi
davos/core/regexps.py
davos/core/regexps.pyi
davos/implementations/__init__.py
davos/implementations/__init__.pyi
davos/implementations/colab.py
davos/implementations/colab.pyi
davos/implementations/ipython_common.py
davos/implementations/ipython_common.pyi
davos/implementations/ipython_post7.py
davos/implementations/ipython_post7.pyi
davos/implementations/ipython_pre7.py
davos/implementations/ipython_pre7.pyi
davos/implementations/js_functions.py
davos/implementations/js_functions.pyi
davos/implementations/jupyter.py
davos/implementations/jupyter.pyi
davos/implementations/python.py
davos/implementations/python.pyi
davos-0.2.3.dist-info/LICENSE
davos-0.2.3.dist-info/METADATA
davos-0.2.3.dist-info/WHEEL
davos-0.2.3.dist-info/top_level.txt
davos-0.2.3.dist-info/RECORD
