Metadata-Version: 2.1
Name: davos
Version: 0.2.3
Summary: Install and manage Python packages at runtime using the "smuggle" statement.
Home-page: https://github.com/ContextLab/davos
Download-URL: https://github.com/ContextLab/davos
Author: Paxton Fitzpatrick, Jeremy Manning
Author-email: contextualdynamics@gmail.com
License: MIT
Keywords: import install package module automatic davos smuggle pip conda
Classifier: Development Status :: 5 - Production/Stable
Classifier: Framework :: IPython
Classifier: Framework :: Jupyter
Classifier: Framework :: Jupyter :: JupyterLab
Classifier: Intended Audience :: Developers
Classifier: Intended Audience :: Education
Classifier: Intended Audience :: Science/Research
Classifier: License :: OSI Approved :: MIT License
Classifier: Operating System :: MacOS
Classifier: Operating System :: POSIX
Classifier: Operating System :: Unix
Classifier: Programming Language :: Python :: 3 :: Only
Classifier: Programming Language :: Python :: 3.6
Classifier: Programming Language :: Python :: 3.7
Classifier: Programming Language :: Python :: 3.8
Classifier: Programming Language :: Python :: 3.9
Classifier: Programming Language :: Python :: 3.10
Classifier: Programming Language :: Python :: 3.11
Classifier: Topic :: System :: Archiving :: Packaging
Classifier: Topic :: System :: Filesystems
Classifier: Topic :: System :: Installation/Setup
Classifier: Topic :: Utilities
Classifier: Typing :: Typed
Requires-Python: >=3.6
License-File: LICENSE
Requires-Dist: packaging
Requires-Dist: importlib-metadata ; python_version < "3.8"
Provides-Extra: tests
Requires-Dist: google-colab ; extra == 'tests'
Requires-Dist: IPython >=5.5.0 ; extra == 'tests'
Requires-Dist: ipykernel >=5.0.0 ; extra == 'tests'
Requires-Dist: mypy ==1.1.1 ; extra == 'tests'
Requires-Dist: pytest ==6.2 ; extra == 'tests'
Requires-Dist: requests ; extra == 'tests'
Requires-Dist: selenium >=3.141 ; extra == 'tests'
Requires-Dist: typing-extensions ; (python_version < "3.9") and extra == 'tests'
Requires-Dist: IPython >=7.3.0 ; (python_version >= "3.8") and extra == 'tests'
Requires-Dist: IPython >=7.15 ; (python_version >= "3.9") and extra == 'tests'
